SFLvault_server-0.9.2-py3.8-nspkg.pth
sflvault/server.py
sflvault/views.py
sflvault/lib/__init__.py
sflvault/lib/vault.py
sflvault/model/__init__.py
sflvault/model/custom_types.py
sflvault/model/meta.py
sflvault/tests/TestVault.py
sflvault/tests/__init__.py
SFLvault_server-0.9.2.dist-info/METADATA
SFLvault_server-0.9.2.dist-info/WHEEL
SFLvault_server-0.9.2.dist-info/namespace_packages.txt
SFLvault_server-0.9.2.dist-info/top_level.txt
SFLvault_server-0.9.2.dist-info/RECORD
