Metadata-Version: 2.1
Name: SFLvault-server
Version: 0.9.2
Summary: Networked credentials store and authentification manager - Server
Home-page: https://www.sflvault.org
Author: Savoir-faire Linux
Author-email: contact@savoirfairelinux.com
License: UNKNOWN
Platform: UNKNOWN
Classifier: Programming Language :: Python
Classifier: Topic :: Internet :: WWW/HTTP
Requires-Dist: SQLAlchemy
Requires-Dist: venusian
Requires-Dist: zope.sqlalchemy
Requires-Dist: decorator
Requires-Dist: pyOpenSSL
